mlflow_modal/__init__.py
mlflow_modal/api.py
mlflow_modal/client.py
mlflow_modal/config.py
mlflow_modal/constants.py
mlflow_modal/stub.py
mlflow_modal-0.1.0.dist-info/LICENSE
mlflow_modal-0.1.0.dist-info/METADATA
mlflow_modal-0.1.0.dist-info/WHEEL
mlflow_modal-0.1.0.dist-info/entry_points.txt
mlflow_modal-0.1.0.dist-info/top_level.txt
mlflow_modal-0.1.0.dist-info/RECORD
