Metadata-Version: 2.1
Name: mlflow-modal
Version: 0.1.0
Summary: Modal MLflow deployment plugin
Home-page: https://github.com/garretthoffman/mlflow-modal
Author: garretthoffman
Author-email: garrett.lee.hoffman@gmail.com
License: Apache 2.0
Keywords: mlflow,modal,serverless,machine learning
Classifier: Topic :: System :: Distributed Computing
Classifier: Operating System :: OS Independent
Classifier: License :: OSI Approved :: MIT License
Classifier: Programming Language :: Python :: 3
Requires-Python: >=3.7
License-File: LICENSE
Requires-Dist: modal-client
Requires-Dist: mlflow (>=1.12.0)
Requires-Dist: pydantic (>=1.10.5)
